contsub/__init__.py
contsub/exceptions.py
contsub/fitfuncs.py
contsub/image_plane.py
contsub/masking.py
contsub/parser/__init__.py
contsub/parser/imcontsub.py
contsub/parser/imcontsub.yaml
contsub/parser/library/__init__.py
contsub/parser/library/dct.yaml
contsub/parser/library/polyn.yaml
contsub/parser/library/spline.yaml
contsub/parser/utils.py
contsub/utils.py
contsub-1.0.5.dist-info/LICENSE
contsub-1.0.5.dist-info/METADATA
contsub-1.0.5.dist-info/WHEEL
contsub-1.0.5.dist-info/entry_points.txt
contsub-1.0.5.dist-info/RECORD
