Metadata-Version: 2.3
Name: contsub
Version: 1.0.5
Summary: Radio astronomy data continuum subtraction tools
License: MIT
Author: Amir Kazemi-Moridani, Sphesihle Makhathini, Mika Naidoo
Requires-Python: >=3.10,<3.13
Classifier: License :: OSI Approved :: MIT License
Classifier: Programming Language :: Python :: 3
Classifier: Programming Language :: Python :: 3.10
Classifier: Programming Language :: Python :: 3.11
Classifier: Programming Language :: Python :: 3.12
Requires-Dist: astropy (>=6.0.0,<7.0.0)
Requires-Dist: numpy (>=1.22.4,<2.0.0)
Requires-Dist: scipy (>=1.12.0,<2.0.0)
Requires-Dist: stimela (>=2.1.2,<3.0.0)
Requires-Dist: xarray-fits
